atomic_ops.py
atomic_ops_ext.cp312-win_amd64.pyd
slick_queue_py.py
slick_queue_py-1.0.0.dist-info/licenses/LICENSE
slick_queue_py-1.0.0.dist-info/METADATA
slick_queue_py-1.0.0.dist-info/WHEEL
slick_queue_py-1.0.0.dist-info/top_level.txt
slick_queue_py-1.0.0.dist-info/RECORD
