Metadata-Version: 2.4
Name: slick_queue_py
Version: 1.0.0
Summary: Lock-free MPMC queue with C++ interoperability via shared memory
Home-page: https://github.com/SlickQuant/slick_queue_py
Author: Slick Quant
Author-email: Slick Quant <slickquant@slickquant.com>
License: MIT
Project-URL: Homepage, https://github.com/SlickQuant/slick_queue_py
Project-URL: Documentation, https://github.com/SlickQuant/slick_queue_py#readme
Project-URL: Repository, https://github.com/SlickQuant/slick_queue_py
Project-URL: Bug Tracker, https://github.com/SlickQuant/slick_queue_py/issues
Keywords: queue,lock-free,atomic,shared-memory,ipc,multiprocessing,mpmc
Classifier: Development Status :: 4 - Beta
Classifier: Intended Audience :: Developers
Classifier: Topic :: Software Development :: Libraries :: Python Modules
Classifier: Topic :: System :: Distributed Computing
Classifier: License :: OSI Approved :: MIT License
Classifier: Programming Language :: Python :: 3
Classifier: Programming Language :: Python :: 3.8
Classifier: Programming Language :: Python :: 3.9
Classifier: Programming Language :: Python :: 3.10
Classifier: Programming Language :: Python :: 3.11
Classifier: Programming Language :: Python :: 3.12
Classifier: Programming Language :: C++
Classifier: Operating System :: Microsoft :: Windows
Classifier: Operating System :: POSIX :: Linux
Classifier: Operating System :: MacOS
Requires-Python: >=3.8
License-File: LICENSE
Dynamic: author
Dynamic: home-page
Dynamic: license-file
Dynamic: requires-python
